istr/__init__.py
istr-1.0.2.dist-info/AUTHORS.rst
istr-1.0.2.dist-info/LICENSE
istr-1.0.2.dist-info/METADATA
istr-1.0.2.dist-info/WHEEL
istr-1.0.2.dist-info/top_level.txt
istr-1.0.2.dist-info/RECORD
