Metadata-Version: 2.1
Name: istr
Version: 1.0.2
Summary: Case-insensitive string implementation.
Home-page: https://github.com/saltstack/istr
Author: Pedro Algarvio
Author-email: pedro@algarvio.me
License: Apache Software License 2.0
Keywords: case-insensitive string match
Platform: UNKNOWN
Classifier: Development Status :: 2 - Pre-Alpha
Classifier: Intended Audience :: Developers
Classifier: License :: OSI Approved :: Apache Software License
Classifier: Natural Language :: English
Classifier: Programming Language :: Python :: 3
Classifier: Programming Language :: Python :: 3.5
Classifier: Programming Language :: Python :: 3.6
Classifier: Programming Language :: Python :: 3.7
Classifier: Programming Language :: Python :: 3.8
